{
  "version": "1.0.0",
  "author": "Ravn Engineering",
  "date": "2026-01-27",
  "abstract": "Modern CLI design patterns following established UX conventions for commands, flags, help text, output formats, error handling, signals, configuration, and distribution.",
  "references": [
    {
      "title": "Command Line Interface Guidelines (clig.dev)",
      "url": "https://clig.dev",
      "description": "Comprehensive guide to modern CLI UX conventions"
    },
    {
      "title": "POSIX Utility Conventions",
      "url": "https://pubs.opengroup.org/onlinepubs/9699919799/basedefs/V1_chap12.html",
      "description": "Standard Unix utility argument syntax"
    },
    {
      "title": "12 Factor CLI Apps",
      "url": "https://medium.com/@jdxcode/12-factor-cli-apps-dd3c227a0e46",
      "description": "Principles for building great command-line applications"
    }
  ]
}
